unicore/__init__.py
unicore-2.0.1.dist-info/METADATA
unicore-2.0.1.dist-info/WHEEL
unicore-2.0.1.dist-info/top_level.txt
unicore-2.0.1.dist-info/RECORD
